<?xml version="1.0" encoding="UTF-8" standalone="yes"?>
<TrustFrameworkPolicy PolicySchemaVersion="0.3.0.0" TenantId="__TenantName__" PolicyId="B2C_1A_sign_up_sign_in" PublicPolicyUri="http://__TenantName__/B2C_1A_sign_up_sign_in" 
  xmlns="http://schemas.microsoft.com/online/cpim/schemas/2013/06" 
  xmlns:xsd="http://www.w3.org/2001/XMLSchema" 
  xmlns:xsi="http://www.w3.org/2001/XMLSchema-instance">
  <BasePolicy>
    <TenantId>__TenantName__</TenantId>
    <PolicyId>B2C_1A_extension</PolicyId>
  </BasePolicy>
  <ClaimsProviders>
    <ClaimsProvider>
      <DisplayName>Self-Asserted</DisplayName>
      <TechnicalProfiles>
        <TechnicalProfile Id="SelfAsserted-LocalAccount-LoginWithRegistrationLink">
          <Metadata>
            <Item Key="SignUpTarget">SelfAsserted-LocalAccount-RegistrationByEmailAndPhone</Item>
          </Metadata>
        </TechnicalProfile>
      </TechnicalProfiles>
    </ClaimsProvider>
  </ClaimsProviders>
  <UserJourneys>
    <UserJourney Id="SignUpOrSignIn">
      <OrchestrationSteps>
        <OrchestrationStep Order="1" Type="CombinedSignInAndSignUp" ContentDefinitionReferenceId="api.signuporsignin">
          <ClaimsProviderSelections>
            <ClaimsProviderSelection ValidationClaimsExchangeId="SelfAsserted-LocalAccount-LoginWithRegistrationLink" />
          </ClaimsProviderSelections>
          <ClaimsExchanges>
            <ClaimsExchange Id="SelfAsserted-LocalAccount-LoginWithRegistrationLink" TechnicalProfileReferenceId="SelfAsserted-LocalAccount-LoginWithRegistrationLink" />
          </ClaimsExchanges>
        </OrchestrationStep>
        <OrchestrationStep Order="2" Type="ClaimsExchange">
          <Preconditions>
            <Precondition Type="ClaimsExist" ExecuteActionsIf="true">
              <Value>userId</Value>
              <Action>SkipThisOrchestrationStep</Action>
            </Precondition>
          </Preconditions>
          <ClaimsExchanges>
            <ClaimsExchange Id="SelfAsserted-LocalAccount-RegistrationByEmailAndPhone" TechnicalProfileReferenceId="SelfAsserted-LocalAccount-RegistrationByEmailAndPhone" />
          </ClaimsExchanges>
        </OrchestrationStep>
        <OrchestrationStep Order="3" Type="ClaimsExchange">
          <ClaimsExchanges>
            <ClaimsExchange Id="AccountStore-GetUserByUserId" TechnicalProfileReferenceId="AccountStore-GetUserByUserId" />
          </ClaimsExchanges>
        </OrchestrationStep>
        <OrchestrationStep Order="4" Type="ClaimsExchange">
          <Preconditions>
            <Precondition Type="ClaimsExist" ExecuteActionsIf="false">
              <Value>email</Value>
              <Action>SkipThisOrchestrationStep</Action>
            </Precondition>
            <Precondition Type="ClaimEquals" ExecuteActionsIf="true">
              <Value>emailVerified</Value>
              <Value>True</Value>
              <Action>SkipThisOrchestrationStep</Action>
            </Precondition>
          </Preconditions>
          <ClaimsExchanges>
            <ClaimsExchange Id="SelfAsserted-LocalAccount-EmailVerification" TechnicalProfileReferenceId="SelfAsserted-LocalAccount-EmailVerification" />
          </ClaimsExchanges>
        </OrchestrationStep>
        <OrchestrationStep Order="5" Type="ClaimsExchange">
          <Preconditions>
            <Precondition Type="ClaimsExist" ExecuteActionsIf="false">
              <Value>email</Value>
              <Action>SkipThisOrchestrationStep</Action>
            </Precondition>
            <Precondition Type="ClaimEquals" ExecuteActionsIf="true">
              <Value>emailVerified</Value>
              <Value>True</Value>
              <Action>SkipThisOrchestrationStep</Action>
            </Precondition>
          </Preconditions>
          <ClaimsExchanges>
            <ClaimsExchange Id="AccountStore-UpdateUserByUserId-SetEmailVerified" TechnicalProfileReferenceId="AccountStore-UpdateUserByUserId-SetEmailVerified" />
          </ClaimsExchanges>
        </OrchestrationStep>
        <OrchestrationStep Order="6" Type="ClaimsExchange">
          <Preconditions>
            <Precondition Type="ClaimsExist" ExecuteActionsIf="false">
              <Value>phone</Value>
              <Action>SkipThisOrchestrationStep</Action>
            </Precondition>
            <Precondition Type="ClaimEquals" ExecuteActionsIf="true">
              <Value>phoneVerified</Value>
              <Value>True</Value>
              <Action>SkipThisOrchestrationStep</Action>
            </Precondition>
          </Preconditions>
          <ClaimsExchanges>
            <ClaimsExchange Id="SelfAsserted-LocalAccount-PhoneVerification" TechnicalProfileReferenceId="SelfAsserted-LocalAccount-PhoneVerification" />
          </ClaimsExchanges>
        </OrchestrationStep>
        <OrchestrationStep Order="7" Type="ClaimsExchange">
          <Preconditions>
            <Precondition Type="ClaimsExist" ExecuteActionsIf="false">
              <Value>phone</Value>
              <Action>SkipThisOrchestrationStep</Action>
            </Precondition>
            <Precondition Type="ClaimEquals" ExecuteActionsIf="true">
              <Value>phoneVerified</Value>
              <Value>True</Value>
              <Action>SkipThisOrchestrationStep</Action>
            </Precondition>
          </Preconditions>
          <ClaimsExchanges>
            <ClaimsExchange Id="AccountStore-UpdateUserByUserId-SetPhoneVerified" TechnicalProfileReferenceId="AccountStore-UpdateUserByUserId-SetPhoneVerified" />
          </ClaimsExchanges>
        </OrchestrationStep>
        <OrchestrationStep Order="8" Type="SendClaims" CpimIssuerTechnicalProfileReferenceId="JwtIssuer" />
      </OrchestrationSteps>
    </UserJourney>
  </UserJourneys>
  <RelyingParty>
    <DefaultUserJourney ReferenceId="SignUpOrSignIn" />
    <TechnicalProfile Id="RelyingParty-SignUpOrSignIn">
      <DisplayName>Relying Party</DisplayName>
      <Protocol Name="OpenIdConnect" />
      <OutputClaims>
        <OutputClaim ClaimTypeReferenceId="newUser" PartnerClaimType="new_user" />
        <OutputClaim ClaimTypeReferenceId="userId" PartnerClaimType="uid" />
        <OutputClaim ClaimTypeReferenceId="email" PartnerClaimType="email" />
        <OutputClaim ClaimTypeReferenceId="emailVerified" PartnerClaimType="email_verified" />
        <OutputClaim ClaimTypeReferenceId="phone" PartnerClaimType="phone_number" />
        <OutputClaim ClaimTypeReferenceId="phoneVerified" PartnerClaimType="phone_number_verified" />
        <OutputClaim ClaimTypeReferenceId="policyId" PartnerClaimType="pid" DefaultValue="{Policy:PolicyId}" AlwaysUseDefaultValue="true" />
      </OutputClaims>
      <SubjectNamingInfo ClaimType="uid" />
    </TechnicalProfile>
  </RelyingParty>
</TrustFrameworkPolicy>
